<?xml version="1.0" encoding="utf-8" ?>
<Game>
	<!-- 手动添加名称缺失道具 -->
	<record alias="Test_N-ShopAccountShippingItem" name2="N-Shop帐号配送物品" />
	<record alias="Test_N-ShopCharacterShippingItem" name2="N-Shop角色配送物品" />
	<record alias="BabaB2_0146" name2="哈迪斯" />
	<record alias="BabaC_0147" name2="哈迪斯" />
	<record alias="InsectTribeGrasshopperA_0148" name2="哈迪斯" />
	<record alias="InsectTribeGrasshopperB_0149" name2="哈迪斯" />
	<record alias="Flazard_0150" name2="哈迪斯" />
	<record alias="DoubleAxe_0151" name2="哈迪斯" />
	<record alias="AncientMechTwinsA_0001" name2="哈迪斯" />
	<record alias="AncientMechTwinsB_0001" name2="哈迪斯" />
	<record alias="Test_Movespeed_Lv1" name2="传说级的敏捷恢复药" />
	<record alias="Test_Sword_Type4_Lv01_101" name2="（英雄）测试用剑Lv50" />
	<record alias="Test_Sword_Type4_Lv01_102" name2="（英雄）测试用剑Lv50" />
	<record alias="Test_Sword_Type4_Lv01_103" name2="（英雄）测试用剑Lv50" />
	<record alias="Test_Sword_Type4_Lv01_104" name2="（英雄）测试用剑Lv50" />
	<record alias="Test_Sword_Type4_Lv01_105" name2="（英雄）测试用剑Lv50" />
	<record alias="Test_Sword_Type4_Lv01_106" name2="（英雄）测试用剑Lv50" />
	<record alias="Test_Sword_Type4_Lv01_107" name2="（英雄）测试用剑Lv50" />
	<record alias="Test_Sword_Type4_Lv01_108" name2="（英雄）测试用剑Lv50" />
	<record alias="Test_Sword_Type4_Lv01_109" name2="（英雄）测试用剑Lv50" />
	<record alias="Test_Sword_Type4_Lv01_110" name2="（英雄）测试用剑Lv50" />
	<record alias="Test_Sword_Type4_Lv02_101" name2="（英雄）测试用剑Lv50" />
	<record alias="Test_Sword_Type4_Lv02_102" name2="（英雄）测试用剑Lv50" />
	<record alias="Test_Sword_Type4_Lv02_103" name2="（英雄）测试用剑Lv50" />
	<record alias="Test_Sword_Type4_Lv02_104" name2="（英雄）测试用剑Lv50" />
	<record alias="Test_Sword_Type4_Lv02_105" name2="（英雄）测试用剑Lv50" />
	<record alias="Test_Sword_Type4_Lv02_106" name2="（英雄）测试用剑Lv50" />
	<record alias="Test_Sword_Type4_Lv02_107" name2="（英雄）测试用剑Lv50" />
	<record alias="Test_Sword_Type4_Lv02_108" name2="（英雄）测试用剑Lv50" />
	<record alias="Test_Sword_Type4_Lv02_109" name2="（英雄）测试用剑Lv50" />
	<record alias="Test_Sword_Type4_Lv02_110" name2="（英雄）测试用剑Lv50" />

	<record alias="Quest_Grocery_SundryItem_0024" name2="史福的工钱袋" />
	<record alias="Quest_Scroll_EliteSkill_0058" name2="破招式一篇" />
	<record alias="Quest_Scroll_EliteSkill_0059" name2="截拳一篇" />
	<record alias="Quest_Scroll_EliteSkill_0060" name2="蒲公英一篇" />
	<record alias="Quest_Scroll_EliteSkill_0061" name2="极限空破一篇" />
	<record alias="Quest_Scroll_EliteSkill_0062" name2="狂风一篇" />
	<record alias="Quest_Scroll_EliteSkill_0063" name2="替身术一篇" />
	<record alias="Quest_Scroll_EliteSkill_0064" name2="流风斩一篇" />
	<record alias="Quest_Scroll_EliteSkill_0065" name2="刺剑式一篇" />
	<record alias="Quest_Scroll_EliteSkill_0066" name2="暴拳一篇" />
	<record alias="Quest_Scroll_EliteSkill_0067" name2="马蜂一篇" />
	<record alias="Quest_Scroll_EliteSkill_0068" name2="炎龙啸一篇" />
	<record alias="Quest_Scroll_EliteSkill_0069" name2="毁灭一篇" />
	<record alias="Quest_Scroll_EliteSkill_0070" name2="震天雷篇" />
	<record alias="Quest_Scroll_EliteSkill_0071" name2="断水流一篇" />
	<record alias="Quest_Scroll_EliteSkill_0072" name2="天隙流光一篇" />
	<record alias="Quest_Scroll_EliteSkill_0073" name2="冲拳一篇" />
	<record alias="Quest_Scroll_EliteSkill_0074" name2="下段斩篇" />
	<record alias="Quest_Scroll_EliteSkill_0075" name2="火莲掌一篇" />
	<record alias="Quest_Scroll_EliteSkill_0076" name2="顿足一篇" />
	<record alias="Quest_Scroll_EliteSkill_0077" name2="斩影一篇" />
	<record alias="Quest_Scroll_EliteSkill_0078" name2="天隙流光一篇" />
	<record alias="Quest_Scroll_EliteSkill_0079" name2="刺剑式二篇" />
	<record alias="Quest_Scroll_EliteSkill_0080" name2="暴拳二篇" />
	<record alias="Quest_Scroll_EliteSkill_0081" name2="马蜂二篇" />
	<record alias="Quest_Scroll_EliteSkill_0082" name2="炎龙啸二篇" />
	<record alias="Quest_Scroll_EliteSkill_0083" name2="毁灭二篇" />
	<record alias="Quest_Scroll_EliteSkill_0084" name2="刺心篇" />
	<record alias="Quest_Scroll_EliteSkill_0085" name2="断水流二篇" />
	<record alias="Quest_Scroll_EliteSkill_0086" name2="天隙流光二篇" />
	<record alias="Quest_Scroll_EliteSkill_0087" name2="冲拳二篇" />
	<record alias="Quest_Scroll_EliteSkill_0088" name2="冲天雷篇" />
	<record alias="Quest_Scroll_EliteSkill_0089" name2="火莲掌二篇" />
	<record alias="Quest_Scroll_EliteSkill_0090" name2="顿足二篇" />
	<record alias="Quest_Scroll_EliteSkill_0091" name2="斩影二篇" />
	<record alias="Quest_Scroll_EliteSkill_0092" name2="天隙流光二篇" />
	<record alias="Quest_Scroll_EliteSkill_0093" name2="格挡二篇" />
	<record alias="Quest_Scroll_EliteSkill_0094" name2="截拳二篇" />
	<record alias="Quest_Scroll_EliteSkill_0095" name2="蒲公英二篇" />
	<record alias="Quest_Scroll_EliteSkill_0096" name2="极限空破二篇" />
	<record alias="Quest_Scroll_EliteSkill_0097" name2="狂风二篇" />
	<record alias="Quest_Scroll_EliteSkill_0098" name2="替身术二篇" />
	<record alias="Quest_Scroll_EliteSkill_0099" name2="流风斩二篇" />
	<record alias="Quest_Scroll_EliteSkill_0100" name2="落剑式一篇" />
	<record alias="Quest_Scroll_EliteSkill_0101" name2="正拳一篇" />
	<record alias="Quest_Scroll_EliteSkill_0102" name2="玫瑰一篇" />
	<record alias="Quest_Scroll_EliteSkill_0103" name2="烈火掌一篇" />
	<record alias="Quest_Scroll_EliteSkill_0104" name2="削骨一篇" />
	<record alias="Quest_Scroll_EliteSkill_0105" name2="迷雾斩一篇" />
	<record alias="Quest_Scroll_EliteSkill_0106" name2="落剑式一篇" />
	<record alias="Quest_Scroll_EliteSkill_0107" name2="落剑式二篇" />
	<record alias="Quest_Scroll_EliteSkill_0108" name2="正拳二篇" />
	<record alias="Quest_Scroll_EliteSkill_0109" name2="玫瑰二篇" />
	<record alias="Quest_Scroll_EliteSkill_0110" name2="烈火掌二篇" />
	<record alias="Quest_Scroll_EliteSkill_0111" name2="削骨二篇" />
	<record alias="Quest_Scroll_EliteSkill_0112" name2="迷雾斩二篇" />
	<record alias="Quest_Scroll_EliteSkill_0113" name2="落剑式二篇" />
	<record alias="Quest_Scroll_Epic10Sub_0001" name2="" />
	<record alias="Quest_Scroll_Epic10Sub_0002" name2="" />
	<record alias="Quest_Scroll_Epic10Sub_0003" name2="" />
	<record alias="General_Grocery_Box_2379" name2="" />
	
	<record alias="GB_General_Accessory_Necklace_0031_701" name2="" />
	<record alias="GB_Event_Grocery_Box_0076" name2="" />
	<record alias="GB_Event_Grocery_Box_0077" name2="" />
	<record alias="GB_Event_Grocery_Box_0078" name2="" />
	<record alias="GB_Event_Grocery_Box_0079" name2="" />
	<record alias="GB_Event_Grocery_Box_0080" name2="" />
	<record alias="GB_General_Grocery_DisplayBox_0035" name2="" />
	<record alias="GB_Event_Grocery_Coin_0296" name2="洪门户牌（旧）" />


	<record alias="GB_General_Weapon_RynSword_0348_BM" name2="" />
	<record alias="GB_General_Weapon_Gauntlet_0349_BM" name2="" />
	<record alias="GB_General_Weapon_Orb_0220_Duplicated" name2="" />
	<record alias="GB_General_Pet1_Skin_0051_100_BM" name2="" />
	<record alias="RS_Cash_Grocery_Potion_0001" name2="" />
	<record alias="GB_General_Grocery_Growth_1002" name2="" />
	<record alias="GB_Event_Grocery_Coin_0020" name2="" />


	<record alias="GB_General_Accessory_Bracelet3_Axe_0098_101" name2="幻天手镯1段" />
	<record alias="GB_General_Accessory_Bracelet3_Axe_0098_102" name2="幻天手镯2段" />
	<record alias="GB_General_Accessory_Bracelet3_Axe_0098_103" name2="幻天手镯3段" />
	<record alias="GB_General_Accessory_Bracelet3_Axe_0098_104" name2="幻天手镯4段" />
	<record alias="GB_General_Accessory_Bracelet3_Axe_0098_105" name2="幻天手镯5段" />
	<record alias="GB_General_Accessory_Bracelet3_Axe_0098_106" name2="幻天手镯6段" />
	<record alias="GB_General_Accessory_Bracelet3_Axe_0098_107" name2="幻天手镯7段" />
	<record alias="GB_General_Accessory_Bracelet3_Axe_0098_108" name2="幻天手镯8段" />
	<record alias="GB_General_Accessory_Bracelet3_Axe_0098_109" name2="幻天手镯9段" />
	<record alias="GB_General_Accessory_Bracelet3_Axe_0098_110" name2="幻天手镯10段" />
	<record alias="GB_General_Accessory_Bracelet3_Axe_0099_101" name2="卓越幻天手镯1段" />
	<record alias="GB_General_Accessory_Bracelet3_Axe_0099_102" name2="卓越幻天手镯2段" />
	<record alias="GB_General_Accessory_Bracelet3_Axe_0099_103" name2="卓越幻天手镯3段" />
	<record alias="GB_General_Accessory_Bracelet3_Axe_0099_104" name2="卓越幻天手镯4段" />
	<record alias="GB_General_Accessory_Bracelet3_Axe_0099_105" name2="卓越幻天手镯5段" />
	<record alias="GB_General_Accessory_Bracelet3_Axe_0099_106" name2="卓越幻天手镯6段" />
	<record alias="GB_General_Accessory_Bracelet3_Axe_0099_107" name2="卓越幻天手镯7段" />
	<record alias="GB_General_Accessory_Bracelet3_Axe_0099_108" name2="卓越幻天手镯8段" />
	<record alias="GB_General_Accessory_Bracelet3_Axe_0099_109" name2="卓越幻天手镯9段" />
	<record alias="GB_General_Accessory_Bracelet3_Axe_0099_110" name2="卓越幻天手镯10段" />
	<record alias="GB_General_Accessory_Bracelet3_Axe_0100_101" name2="极限幻天手镯1段" />
	<record alias="GB_General_Accessory_Bracelet3_Axe_0100_102" name2="极限幻天手镯2段" />
	<record alias="GB_General_Accessory_Bracelet3_Axe_0100_103" name2="极限幻天手镯3段" />
	<record alias="GB_General_Accessory_Bracelet3_Axe_0100_104" name2="极限幻天手镯4段" />
	<record alias="GB_General_Accessory_Bracelet3_Axe_0100_105" name2="极限幻天手镯5段" />
	<record alias="GB_General_Accessory_Bracelet3_Axe_0100_106" name2="极限幻天手镯6段" />
	<record alias="GB_General_Accessory_Bracelet3_Axe_0100_107" name2="极限幻天手镯7段" />
	<record alias="GB_General_Accessory_Bracelet3_Axe_0100_108" name2="极限幻天手镯8段" />
	<record alias="GB_General_Accessory_Bracelet3_Axe_0100_109" name2="极限幻天手镯9段" />
	<record alias="GB_General_Accessory_Bracelet3_Axe_0100_110" name2="极限幻天手镯10段" />
	<record alias="GB_General_Accessory_Bracelet3_Axe_0101_101" name2="超越幻天手镯1段" />
	<record alias="GB_General_Accessory_Bracelet3_Axe_0101_102" name2="超越幻天手镯2段" />
	<record alias="GB_General_Accessory_Bracelet3_Axe_0101_103" name2="超越幻天手镯3段" />
	<record alias="GB_General_Accessory_Bracelet3_Axe_0101_104" name2="超越幻天手镯4段" />
	<record alias="GB_General_Accessory_Bracelet3_Axe_0101_105" name2="超越幻天手镯5段" />
	<record alias="GB_General_Accessory_Bracelet3_Axe_0101_106" name2="超越幻天手镯6段" />
	<record alias="GB_General_Accessory_Bracelet3_Axe_0101_107" name2="超越幻天手镯7段" />
	<record alias="GB_General_Accessory_Bracelet3_Axe_0101_108" name2="超越幻天手镯8段" />
	<record alias="GB_General_Accessory_Bracelet3_Axe_0101_109" name2="超越幻天手镯9段" />
	<record alias="GB_General_Accessory_Bracelet3_Axe_0101_110" name2="超越幻天手镯10段" />
</Game>